mplot.py
mplot_plots-1.3.dist-info/LICENSE.txt
mplot_plots-1.3.dist-info/METADATA
mplot_plots-1.3.dist-info/WHEEL
mplot_plots-1.3.dist-info/top_level.txt
mplot_plots-1.3.dist-info/RECORD
