Metadata-Version: 2.1
Name: mplot-plots
Version: 1.3
Summary: Diagnostic plots for linear model
Home-page: https://gitlab.com/gspwanyama97/mplot_plot
Author: Geofrey Wanyama
Author-email: wanyamag17@gmail.com
License: UNKNOWN
Platform: UNKNOWN
Classifier: Programming Language :: Python :: 3
Classifier: Programming Language :: Python :: 3.6
Classifier: Programming Language :: Python :: 3.7
Classifier: License :: OSI Approved :: MIT License
Classifier: Operating System :: OS Independent
License-File: LICENSE.txt
